azura/__init__.py
azura/geography.py
azura/percents.py
azura-0.1.1.dist-info/METADATA
azura-0.1.1.dist-info/WHEEL
azura-0.1.1.dist-info/top_level.txt
azura-0.1.1.dist-info/RECORD
