Metadata-Version: 2.1
Name: azura
Version: 0.1.1
Summary: Azura is an add-on to the math library. Made by Laksh Patel, cannot be distributed as your own.
Home-page: UNKNOWN
Author: Laksh Patel
Author-email: laksh2008patel@gmail.com
License: MIT
Platform: UNKNOWN
Classifier: Intended Audience :: Developers
Classifier: License :: OSI Approved :: MIT License
Classifier: Programming Language :: Python
Classifier: Programming Language :: Python :: 3
Classifier: Programming Language :: Python :: 3.6
Classifier: Programming Language :: Python :: 3.7
Classifier: Programming Language :: Python :: 3.8
Classifier: Programming Language :: Python :: 3.9
Classifier: Operating System :: OS Independent
Requires-Dist: numpy
